offat/__init__.py
offat/__main__.py
offat/api/__init__.py
offat/api/__main__.py
offat/api/app.py
offat/api/auth_utils.py
offat/api/config.py
offat/api/jobs.py
offat/api/schema.py
offat/config_data_handler.py
offat/http.py
offat/logger.py
offat/parsers/__init__.py
offat/parsers/openapi.py
offat/parsers/parser.py
offat/parsers/swagger.py
offat/report/__init__.py
offat/report/generator.py
offat/report/summary.py
offat/report/templates/__init__.py
offat/report/templates/report.html
offat/report/templates/table.py
offat/tester/__init__.py
offat/tester/fuzzer.py
offat/tester/generator.py
offat/tester/handler.py
offat/tester/post_test_processor.py
offat/tester/regexs.py
offat/tester/runner.py
offat/tester/tester_utils.py
offat/tests/__init__.py
offat/tests/parsers/__init__.py
offat/tests/parsers/test_parser.py
offat/tests/self_signed/__init__.py
offat/tests/self_signed/self_signed_server_tester.py
offat/tests/testers/__init__.py
offat/tests/testers/test_fuzzer.py
offat/tests/utils/__init__.py
offat/tests/utils/test_parse_server_url.py
offat/tests/utils/test_url_validations.py
offat/utils.py
offat-0.19.4.dist-info/METADATA
offat-0.19.4.dist-info/WHEEL
offat-0.19.4.dist-info/entry_points.txt
offat-0.19.4.dist-info/RECORD
