Metadata-Version: 2.3
Name: offat
Version: 0.19.4
Summary: Offensive API tester tool automates checks for common API vulnerabilities
License: MIT
Author: Dhrumil Mistry
Author-email: dhrumil.mistry@owasp.org
Requires-Python: >=3.10,<4.0
Classifier: License :: OSI Approved :: MIT License
Classifier: Programming Language :: Python :: 3
Classifier: Programming Language :: Python :: 3.10
Classifier: Programming Language :: Python :: 3.11
Classifier: Programming Language :: Python :: 3.12
Classifier: Programming Language :: Python :: 3.13
Provides-Extra: api
Requires-Dist: aiohttp (>=3.8.4,<4.0.0)
Requires-Dist: aiolimiter (>=1.1.0,<2.0.0)
Requires-Dist: fastapi (>=0.115.2,<0.116.0) ; extra == "api"
Requires-Dist: openapi-spec-validator (>=0.7.1,<0.8.0)
Requires-Dist: python-dotenv (>=1.0.0,<2.0.0) ; extra == "api"
Requires-Dist: pyyaml (>=6.0,<7.0)
Requires-Dist: redis (>=5.0.0,<6.0.0) ; extra == "api"
Requires-Dist: rich (>=13.7.0,<14.0.0)
Requires-Dist: rq (>=1.15.1,<2.0.0) ; extra == "api"
Requires-Dist: setuptools (>=69.0.3)
Requires-Dist: tenacity (>=8.2.3,<9.0.0)
Requires-Dist: uvicorn[standard] (>=0.23.2,<0.24.0) ; extra == "api"
Project-URL: Bug Tracker, https://github.com/OWASP/OFFAT/issues
Project-URL: Home, https://github.com/OWASP/OFFAT
Project-URL: Support, https://github.com/sponsors/OWASP/
